CHANGES.rst
CONTRIBUTORS.rst
MANIFEST.in
README.rst
setup.cfg
setup.py
docs/LICENSE.GPL
docs/LICENSE.txt
src/collective/__init__.py
src/collective.opendata.egg-info/PKG-INFO
src/collective.opendata.egg-info/SOURCES.txt
src/collective.opendata.egg-info/dependency_links.txt
src/collective.opendata.egg-info/entry_points.txt
src/collective.opendata.egg-info/namespace_packages.txt
src/collective.opendata.egg-info/not-zip-safe
src/collective.opendata.egg-info/requires.txt
src/collective.opendata.egg-info/top_level.txt
src/collective/opendata/__init__.py
src/collective/opendata/config.py
src/collective/opendata/configure.zcml
src/collective/opendata/interfaces.py
src/collective/opendata/testing.py
src/collective/opendata/utils.py
src/collective/opendata/browser/__init__.py
src/collective/opendata/browser/apidata.py
src/collective/opendata/browser/configure.zcml
src/collective/opendata/browser/opendata.py
src/collective/opendata/browser/templates/opendata.pt
src/collective/opendata/locales/collective.opendata.pot
src/collective/opendata/locales/manual.pot
src/collective/opendata/locales/es/LC_MESSAGES/collective.opendata.po
src/collective/opendata/locales/pt_BR/LC_MESSAGES/collective.opendata.po
src/collective/opendata/plugins/__init__.py
src/collective/opendata/plugins/configure.zcml
src/collective/opendata/plugins/cms/__init__.py
src/collective/opendata/plugins/cms/configure.zcml
src/collective/opendata/plugins/content/__init__.py
src/collective/opendata/plugins/content/configure.zcml
src/collective/opendata/plugins/content/dcelements.rdf
src/collective/opendata/tests/__init__.py
src/collective/opendata/tests/test_apidata.py
src/collective/opendata/tests/test_plugin_cms.py
src/collective/opendata/tests/test_utils.py