Metadata-Version: 1.1
Name: collective.opendata
Version: 1.0a2
Summary: A generic implementation of the Open Data Protocol for Plone.
Home-page: https://github.com/plonegovbr/collective.opendata
Author: PloneGov-BR
Author-email: gov@plone.org.br
License: UNKNOWN
Keywords: plone open data opendata odata api
Platform: UNKNOWN
Classifier: Development Status :: 3 - Alpha
Classifier: Environment :: Web Environment
Classifier: Framework :: Plone
Classifier: Framework :: Plone :: 4.3
Classifier: Intended Audience :: System Administrators
Classifier: License :: OSI Approved :: GNU General Public License v2 (GPLv2)
Classifier: Operating System :: OS Independent
Classifier: Programming Language :: Python
Classifier: Programming Language :: Python :: 2.7
Classifier: Topic :: Software Development :: Libraries :: Python Modules
